[{"model":"community.rating","pk":6973,"fields":{"rating":5,"content":"별로예요","movie":10064,"user":1,"created_at":"2021-11-20T17:18:05.395Z","like_users":[],"dlike_users":[]}},{"model":"community.rating","pk":6974,"fields":{"rating":7,"content":"그저 그래요","movie":29161,"user":1,"created_at":"2021-11-20T17:18:06.785Z","like_users":[],"dlike_users":[]}},{"model":"community.rating","pk":6975,"fields":{"rating":7,"content":"그저 그래요","movie":5279,"user":1,"created_at":"2021-11-20T17:18:07.842Z","like_users":[],"dlike_users":[]}},{"model":"community.rating","pk":6976,"fields":{"rating":5,"content":"별로예요","movie":9713,"user":1,"created_at":"2021-11-20T17:18:09.052Z","like_users":[],"dlike_users":[]}},{"model":"community.rating","pk":6977,"fields":{"rating":6,"content":"별로예요","movie":23742,"user":1,"created_at":"2021-11-20T17:18:10.331Z","like_users":[],"dlike_users":[]}},{"model":"community.rating","pk":6978,"fields":{"rating":7,"content":"괜찮게 봤어요","movie":10707,"user":1,"created_at":"2021-11-20T17:18:11.480Z","like_users":[],"dlike_users":[]}},{"model":"community.rating","pk":6979,"fields":{"rating":5,"content":"별로예요","movie":2017,"user":1,"created_at":"2021-11-20T17:18:12.790Z","like_users":[],"dlike_users":[]}},{"model":"community.rating","pk":6980,"fields":{"rating":7,"content":"그저 그래요","movie":1921,"user":1,"created_at":"2021-11-20T17:18:13.859Z","like_users":[],"dlike_users":[]}},{"model":"community.rating","pk":6981,"fields":{"rating":6,"content":"별로예요","movie":23410,"user":1,"created_at":"2021-11-20T17:18:14.942Z","like_users":[],"dlike_users":[]}},{"model":"community.rating","pk":6982,"fields":{"rating":7,"content":"괜찮게 봤어요","movie":214314,"user":1,"created_at":"2021-11-20T17:18:15.635Z","like_users":[],"dlike_users":[]}}]