[{"model":"community.rating","pk":4675,"fields":{"rating":6,"content":"그저 그래요","movie":11560,"user":1,"created_at":"2021-11-20T16:30:19.314Z","like_users":[],"dlike_users":[]}},{"model":"community.rating","pk":4676,"fields":{"rating":7,"content":"괜찮게 봤어요","movie":1645,"user":1,"created_at":"2021-11-20T16:30:20.170Z","like_users":[],"dlike_users":[]}},{"model":"community.rating","pk":4677,"fields":{"rating":6,"content":"그저 그래요","movie":183662,"user":1,"created_at":"2021-11-20T16:30:21.295Z","like_users":[],"dlike_users":[]}},{"model":"community.rating","pk":4678,"fields":{"rating":6,"content":"그저 그래요","movie":4244,"user":1,"created_at":"2021-11-20T16:30:22.483Z","like_users":[],"dlike_users":[]}},{"model":"community.rating","pk":4679,"fields":{"rating":6,"content":"그저 그래요","movie":11418,"user":1,"created_at":"2021-11-20T16:30:23.812Z","like_users":[],"dlike_users":[]}},{"model":"community.rating","pk":4680,"fields":{"rating":8,"content":"괜찮게 봤어요","movie":9516,"user":1,"created_at":"2021-11-20T16:30:24.916Z","like_users":[],"dlike_users":[]}},{"model":"community.rating","pk":4681,"fields":{"rating":7,"content":"괜찮게 봤어요","movie":333352,"user":1,"created_at":"2021-11-20T16:30:26.097Z","like_users":[],"dlike_users":[]}},{"model":"community.rating","pk":4682,"fields":{"rating":7,"content":"괜찮게 봤어요","movie":285783,"user":1,"created_at":"2021-11-20T16:30:27.368Z","like_users":[],"dlike_users":[]}},{"model":"community.rating","pk":4683,"fields":{"rating":7,"content":"괜찮게 봤어요","movie":15362,"user":1,"created_at":"2021-11-20T16:30:28.812Z","like_users":[],"dlike_users":[]}},{"model":"community.rating","pk":4684,"fields":{"rating":7,"content":"괜찮게 봤어요","movie":77016,"user":1,"created_at":"2021-11-20T16:30:29.744Z","like_users":[],"dlike_users":[]}}]